ionwizard/__init__.py
ionwizard/_version.py
ionwizard/container_wizard.py
ionwizard/env_variables.py
ionwizard/input_args.py
ionwizard/install_project.py
ionwizard/library_wizard.py
ionwizard/notifications.py
ionwizard/offline_validation.py
ionwizard/validate.py
ionwizard/write_config.py
ionwizard-0.2.2.dist-info/METADATA
ionwizard-0.2.2.dist-info/WHEEL
ionwizard-0.2.2.dist-info/entry_points.txt
ionwizard-0.2.2.dist-info/licenses/LICENSE.md
ionwizard-0.2.2.dist-info/RECORD
