Metadata-Version: 2.4
Name: ionwizard
Version: 0.2.2
Summary: Installation tools for Ionworks software
License: # Ionworks Software License
License-File: LICENSE.md
Requires-Python: >=3.10
Requires-Dist: cryptography
Requires-Dist: platformdirs
Requires-Dist: py-machineid
Requires-Dist: pynacl
Requires-Dist: python-dateutil
Requires-Dist: pyyaml
Requires-Dist: requests
Requires-Dist: toml
Provides-Extra: dev
Requires-Dist: myst-parser; extra == 'dev'
Requires-Dist: pytest; extra == 'dev'
Requires-Dist: pytest-mock; extra == 'dev'
Requires-Dist: sphinx; extra == 'dev'
Requires-Dist: sphinx-rtd-theme; extra == 'dev'
